adk/ext/__init__.py
adk/ext/agents/__init__.py
adk/ext/agents/skippable_sequential_agent.py
adk/ext/sessions/__init__.py
adk/ext/sessions/firestore_session_svc.py
adk/ext/sessions/redis_session_svc.py
adk_ext-0.0.3.dist-info/licenses/LICENSE
adk_ext-0.0.3.dist-info/METADATA
adk_ext-0.0.3.dist-info/WHEEL
adk_ext-0.0.3.dist-info/top_level.txt
adk_ext-0.0.3.dist-info/RECORD
