Metadata-Version: 2.4
Name: adk-ext
Version: 0.0.3
Summary: A comprehensive Python extension library for Google's Agent Development Kit (ADK)
Author-email: Nanda Gopalan <oss@nandlabs.io>
Project-URL: Homepage, https://github.com/nandlabs/adk-ext-python
Project-URL: Bug Tracker, https://github.com/nandlabs/adk-ext-python/issues
Project-URL: Documentation, https://github.com/nandlabs/adk-ext-python
Keywords: adk,google,agent,extension
Classifier: Development Status :: 3 - Alpha
Classifier: Intended Audience :: Developers
Classifier: License :: OSI Approved :: MIT License
Classifier: Programming Language :: Python :: 3
Classifier: Programming Language :: Python :: 3.9
Classifier: Programming Language :: Python :: 3.10
Classifier: Programming Language :: Python :: 3.11
Requires-Python: >=3.9
License-File: LICENSE
Requires-Dist: google-adk>=1.1.0
Provides-Extra: dev
Requires-Dist: pytest>=7.0.0; extra == "dev"
Requires-Dist: pytest-cov>=4.0.0; extra == "dev"
Requires-Dist: black>=23.0.0; extra == "dev"
Requires-Dist: isort>=5.0.0; extra == "dev"
Requires-Dist: flake8>=6.0.0; extra == "dev"
Requires-Dist: mypy>=1.0.0; extra == "dev"
Provides-Extra: docs
Requires-Dist: sphinx>=6.0.0; extra == "docs"
Requires-Dist: sphinx-rtd-theme>=1.0.0; extra == "docs"
Provides-Extra: firestore
Requires-Dist: google-cloud-firestore>=2.11.0; extra == "firestore"
Provides-Extra: redis
Requires-Dist: redis>=6.0.0; extra == "redis"
Provides-Extra: all
Requires-Dist: google-adk>=1.1.0; extra == "all"
Requires-Dist: google-cloud-firestore>=2.11.0; extra == "all"
Requires-Dist: redis>=6.0.0; extra == "all"
Dynamic: license-file
